README.rst
setup.py
dota2/__init__.py
dota2/client.py
dota2/common_enums.py
dota2/enums.py
dota2/msg.py
dota2/proto_enums.py
dota2.egg-info/PKG-INFO
dota2.egg-info/SOURCES.txt
dota2.egg-info/dependency_links.txt
dota2.egg-info/requires.txt
dota2.egg-info/top_level.txt
dota2.egg-info/zip-safe
dota2/features/__init__.py
dota2/features/chat.py
dota2/features/lobby.py
dota2/features/match.py
dota2/features/party.py
dota2/features/player.py
dota2/features/sharedobjects.py
dota2/protobufs/__init__.py
dota2/protobufs/base_gcmessages_pb2.py
dota2/protobufs/dota_client_enums_pb2.py
dota2/protobufs/dota_gcmessages_client_chat_pb2.py
dota2/protobufs/dota_gcmessages_client_fantasy_pb2.py
dota2/protobufs/dota_gcmessages_client_guild_pb2.py
dota2/protobufs/dota_gcmessages_client_match_management_pb2.py
dota2/protobufs/dota_gcmessages_client_pb2.py
dota2/protobufs/dota_gcmessages_client_team_pb2.py
dota2/protobufs/dota_gcmessages_client_tournament_pb2.py
dota2/protobufs/dota_gcmessages_client_watch_pb2.py
dota2/protobufs/dota_gcmessages_common_match_management_pb2.py
dota2/protobufs/dota_gcmessages_common_pb2.py
dota2/protobufs/dota_gcmessages_msgid_pb2.py
dota2/protobufs/dota_match_metadata_pb2.py
dota2/protobufs/dota_shared_enums_pb2.py
dota2/protobufs/econ_gcmessages_pb2.py
dota2/protobufs/econ_shared_enums_pb2.py
dota2/protobufs/gcsdk_gcmessages_pb2.py
dota2/protobufs/gcsystemmsgs_pb2.py
dota2/protobufs/steammessages_pb2.py
dota2/util/__init__.py